{
  "extensions": [
    {
      "type": "@Common.Revealer",
      "contextTypes": [
        "SDK.Resource"
      ],
      "destination": "Application panel",
      "className": "Resources.ResourcesPanel.ResourceRevealer"
    },
    {
      "type": "@Common.Revealer",
      "contextTypes": [
        "SDK.CookieReference"
      ],
      "destination": "Application panel",
      "className": "Resources.ResourcesPanel.CookieReferenceRevealer"
    }
  ],
  "dependencies": [
    "source_frame",
    "cookie_table",
    "inline_editor",
    "data_grid",
    "components",
    "object_ui",
    "perf_ui",
    "mobile_throttling",
    "network",
    "sources",
    "browser_sdk",
    "i18n"
  ],
  "modules": [
    "resources-legacy.js"
  ],
  "resources": [
    "appManifestView.css",
    "backgroundServiceView.css",
    "clearStorageView.css",
    "indexedDBViews.css",
    "resourcesPanel.css",
    "resourcesSidebar.css",
    "serviceWorkerCacheViews.css",
    "serviceWorkersView.css",
    "serviceWorkerUpdateCycleView.css",
    "cookieItemsView.css",
    "frameDetailsReportView.css"
  ]
}
